__init__.py
gavel_owl/__init__.py
gavel_owl/cli.py
gavel_owl/dialects/__init__.py
gavel_owl/dialects/fowl/FOLSymbol.py
gavel_owl/dialects/fowl/__init__.py
gavel_owl/dialects/fowl/dialect.py
gavel_owl/dialects/fowl/macleod_clif_parser.py
gavel_owl/dialects/fowl/ontology_inference.py
gavel_owl/dialects/fowl/parser.py
gavel_owl/dialects/owl/__init__.py
gavel_owl/dialects/owl/dialect.py
gavel_owl/dialects/owl/parser.py
gavel_owl/jars/__init__.py
gavel_owl-0.2.0.dist-info/licenses/AUTHORS.rst
gavel_owl-0.2.0.dist-info/licenses/LICENSE
gavel_owl-0.2.0.dist-info/METADATA
gavel_owl-0.2.0.dist-info/WHEEL
gavel_owl-0.2.0.dist-info/entry_points.txt
gavel_owl-0.2.0.dist-info/top_level.txt
gavel_owl-0.2.0.dist-info/RECORD
