Metadata-Version: 2.4
Name: gavel-owl
Version: 0.2.0
Summary: An extension for gavel introducing OWL translations.
Home-page: https://github.com/gavel-tool/python-gavel-owl
Author: Anna Kleinau, Simon Flügel, Martin Glauer
Author-email: martin.glauer@ovgu.de
Project-URL: Documentation, https://python-gavel-owl.readthedocs.io/
Project-URL: Changelog, https://python-gavel-owl.readthedocs.io/en/latest/changelog.html
Project-URL: Issue Tracker, https://github.com/gavel-tool/python-gavel-owl/issues
Classifier: Development Status :: 5 - Production/Stable
Classifier: Intended Audience :: Developers
Classifier: Operating System :: Unix
Classifier: Operating System :: POSIX
Classifier: Operating System :: Microsoft :: Windows
Classifier: Programming Language :: Python
Classifier: Programming Language :: Python :: 3
Classifier: Programming Language :: Python :: 3.5
Classifier: Programming Language :: Python :: 3.6
Classifier: Programming Language :: Python :: 3.7
Classifier: Programming Language :: Python :: 3.8
Classifier: Programming Language :: Python :: 3.9
Classifier: Programming Language :: Python :: Implementation :: CPython
Classifier: Programming Language :: Python :: Implementation :: PyPy
Classifier: Topic :: Utilities
Requires-Python: >=3, !=3.0.*, !=3.1.*, !=3.2.*, !=3.3.*, !=3.4.*
License-File: LICENSE
License-File: AUTHORS.rst
Requires-Dist: click
Requires-Dist: gavel>=0.1.0
Requires-Dist: py4j
Requires-Dist: ply
Dynamic: author
Dynamic: author-email
Dynamic: classifier
Dynamic: description
Dynamic: home-page
Dynamic: license-file
Dynamic: project-url
Dynamic: requires-dist
Dynamic: requires-python
Dynamic: summary
